{
  "jobs": {
    "javabase-review": {
      "learning_progress": "",
      "last_sent_date": "2026-04-22",
      "last_email_subject": "javabase 复习提醒",
      "last_review_content": "- Java 核心语法与基本数据类型深度回顾\n- 面向对象四大特性（封装、继承、多态、抽象）查漏补缺\n- 单例模式与工厂模式的手写实现与原理进阶\n- List、Map 集合框架数据结构与底层原理强化\n- 线程生命周期同步机制及锁的面试考点速攻\n- JVM 内存区域划分与垃圾回收算法基础复盘\n- 运行时异常与检查型异常的区分与处理策略回顾\n- IO 流与 NIO 核心类的使用熟练化训练",
      "review_count": 3,
      "history": [
        {
          "sent_at": "2026-04-16",
          "subject": "javabase 复习提醒",
          "content": "- 理解 Java 编程语言的核心概念与语法基础\n- 掌握面向对象编程的四大特性：封装、继承、多态与抽象\n- 熟练使用 JDK8 手写单例模式、工厂模式等基础设计模式\n- 深入理解 Java 集合框架，特别是 List、Map 及内部原理\n- 掌握多线程编程基础，理解线程生命周期与常见同步方式\n- 熟悉 JVM 内存模型，包括堆、栈、方法区的基本划分\n- 了解异常处理机制，掌握常用运行时异常与检查型异常的区分\n- 理解 IO 流与 NIO 的基本概念及常用类的使用",
          "workflow_run_id": "a0f45309-dabf-46dc-a702-fb9c521fe765"
        },
        {
          "sent_at": "2026-04-19",
          "subject": "javabase 复习提醒",
          "content": "- Java 核心语法与基本数据类型回顾\n- 面向对象四大特性（封装、继承、多态、抽象）巩固\n- 单例模式与工厂模式的手写实现与原理\n- List、Map 集合框架数据结构与底层原理\n- 线程生命周期同步机制及锁的面试考点\n- JVM 内存区域划分与垃圾回收算法基础\n- 运行时异常与检查型异常的区分与处理策略\n- IO 流与 NIO 核心类的使用",
          "workflow_run_id": "0349a905-1ddf-4a30-9bc0-120e54362a31"
        },
        {
          "sent_at": "2026-04-22",
          "subject": "javabase 复习提醒",
          "content": "- Java 核心语法与基本数据类型深度回顾\n- 面向对象四大特性（封装、继承、多态、抽象）查漏补缺\n- 单例模式与工厂模式的手写实现与原理进阶\n- List、Map 集合框架数据结构与底层原理强化\n- 线程生命周期同步机制及锁的面试考点速攻\n- JVM 内存区域划分与垃圾回收算法基础复盘\n- 运行时异常与检查型异常的区分与处理策略回顾\n- IO 流与 NIO 核心类的使用熟练化训练",
          "workflow_run_id": "684fd97f-57ba-432b-a625-a4abf74fbbae"
        }
      ]
    }
  }
}
